weycop/__init__.py
weycop/client.py
weycop/exceptions.py
weycop/models.py
weycop-2.1.1.dist-info/licenses/LICENSE
weycop-2.1.1.dist-info/METADATA
weycop-2.1.1.dist-info/WHEEL
weycop-2.1.1.dist-info/top_level.txt
weycop-2.1.1.dist-info/RECORD
